nonebot_plugin_bot_tap/Microsoft_YaHei_Consolas_Regular.ttf
nonebot_plugin_bot_tap/__init__.py
nonebot_plugin_bot_tap/config.py
nonebot_plugin_bot_tap/utils.py
nonebot_plugin_bot_tap-0.0.4.dist-info/METADATA
nonebot_plugin_bot_tap-0.0.4.dist-info/WHEEL
nonebot_plugin_bot_tap-0.0.4.dist-info/RECORD
