Metadata-Version: 2.3
Name: nonebot-plugin-bot-tap
Version: 0.0.4
Summary: 在 NoneBot 中管理你的 NoneBot 吧！
License: GPL3
Author: 【夜风】NightWind
Author-email: 2125714976@qq.com
Requires-Python: >=3.9
Classifier: License :: Other/Proprietary License
Classifier: Programming Language :: Python :: 3
Classifier: Programming Language :: Python :: 3.9
Classifier: Programming Language :: Python :: 3.10
Classifier: Programming Language :: Python :: 3.11
Classifier: Programming Language :: Python :: 3.12
Classifier: Programming Language :: Python :: 3.13
Requires-Dist: httpx (>=0.22.0)
Requires-Dist: nonebot-adapter-onebot (>=2.3.0)
Requires-Dist: nonebot-plugin-send-anything-anywhere (>=0.7.1)
Requires-Dist: nonebot2 (>=2.3.0,<3.0.0)
Requires-Dist: nonebot_plugin_session (>=0.3.2)
Requires-Dist: pillow (>=11.1.0)
Project-URL: Documentation, https://github.com/NonebotGUI/nonebot-plugin-bot-tap#README.md
Project-URL: Homepage, https://github.com/NonebotGUI/nonebot-plugin-bot-tap
Project-URL: Repository, https://github.com/NonebotGUI/nonebot-plugin-bot-tap
